[
  {
    "description": "",
    "elements": [
      {
        "description": "",
        "id": "vehicles-module-functionality;adding-a-vehicle-and-verifying-that-its-properties-are-also-visible-in-vehicle-details-page",
        "keyword": "Scenario Outline",
        "line": 18,
        "name": "Adding a vehicle and verifying that its properties are also visible in Vehicle Details page",
        "steps": [
          {
            "arguments": [],
            "keyword": "Given ",
            "line": 5,
            "name": "Navigate to Dashboard with \"english\" language",
            "result": {
              "status": "passed",
              "duration": 3504000000
            }
          },
          {
            "arguments": [],
            "keyword": "Then ",
            "line": 6,
            "name": "verify that dashboard page tab name contains QUGEM",
            "result": {
              "status": "passed",
              "duration": 1012000000
            }
          },
          {
            "arguments": [],
            "keyword": "When ",
            "line": 7,
            "name": "click to Vehicles module",
            "result": {
              "status": "passed",
              "duration": 91000000
            }
          },
          {
            "arguments": [],
            "keyword": "Then ",
            "line": 8,
            "name": "delete if a vehicle is added for test purpose ,Vehicle plate is \"TE ST 3000\"",
            "result": {
              "status": "passed",
              "duration": 6385000000
            }
          },
          {
            "arguments": [],
            "keyword": "Then ",
            "line": 11,
            "name": "click add vehicle button",
            "result": {
              "status": "passed",
              "duration": 90000000
            }
          },
          {
            "arguments": [],
            "keyword": "Then ",
            "line": 12,
            "name": "fill in the input boxes of \"TE ST 3000\" , \"Mercedes\" , \"A3\",\"LKW\",\"2012\" \"2015\" , \"100000\" and \"20000\"",
            "result": {
              "status": "passed",
              "duration": 458000000
            }
          },
          {
            "arguments": [],
            "keyword": "Then ",
            "line": 13,
            "name": "click save changes in vehicles edit page",
            "result": {
              "status": "passed",
              "duration": 1284000000
            }
          },
          {
            "arguments": [],
            "keyword": "Then ",
            "line": 14,
            "name": "verify alert message text is \"Vehicle was added successfully..\"",
            "result": {
              "status": "passed",
              "duration": 9000000
            }
          },
          {
            "keyword": "After",
            "hidden": true,
            "result": {
              "status": "passed",
              "duration": 294000000
            }
          }
        ],
        "tags": [
          {
            "name": "@only"
          }
        ],
        "type": "scenario"
      }
    ],
    "id": "chromium-›-vehicles-module-functionality",
    "line": 2,
    "keyword": "Feature",
    "name": "Vehicles Module functionality",
    "tags": [
      {
        "name": "@only",
        "line": 1
      }
    ],
    "uri": ".cucumber/features/vehicles.feature"
  }
]